{
  "major": "586d234f5f07127674152c42",
  "description": "当然死记硬背谁都会，填鸭式学习难免让人感到枯燥无味，导致不是早早放弃就是基础不牢。那有什么好的方法来学习日语？想要听歌学日语，要的不仅是由听歌所得到的潜移默化的语感，还要得到的，是从歌曲中折射出的日本本身的文化之美，内涵之深。这次，就把这一切，交给两位美女老师来演绎吧！\n",
  "deleted": false,
  "bigImage": "http://imgs.wanmen.org/99d08762c54636ae17564f7d9f39938a.png",
  "finishedAt": "2017-06-09T08:38:48.184Z",
  "introductionVideoUrl": "http://media.wanmen.org/5c9e04d053e31ea590f11a8a41204fe3_pc_high.m3u8",
  "smallImage": "http://imgs.wanmen.org/7b50ce5178c08f7b75983a606dab1353.png",
  "updatedAt": "2018-01-02T09:02:45.401Z",
  "teacher": {
    "name": "刘苏曼、李茉白",
    "description": "刘苏曼，北京大学日语博士在读，著有《简单日语极速入门》。曾获第16届中日友好之声日语演讲比赛低年级组第1名，曾赴日本京都大学交换留学。多场口译、笔译、主持经验，曾负责东北亚学生论坛即席翻译。\n\n李茉白 。初一开始至今日语专业12年，保送北京外国语大学本硕；前新东方前人气日语教师 新教师PK赛第一名；前北京外国语大学日语二外教师；JLPT考试N1满分 日语专业八级优秀；CATTI全国翻译资格口译二级。\n\n",
    "avatar": "http://imgs.wanmen.org/6cd475b81fe753da4731cb2dba1c2259.png",
    "id": "5879d1fc0389ac22aad6d56f"
  },
  "createdAt": "2017-01-14T07:36:25.021Z",
  "hide": false,
  "name": "北大博士带你听歌学日语",
  "isPinned": false,
  "expiration": 12,
  "deletedAt": null,
  "streamKey": "818073138593054",
  "price": 98,
  "openingAt": "2017-01-19T12:00:00.000Z",
  "numOfClasses": 3,
  "specialTrainingOrder": 0,
  "videoCount": 10,
  "tag": "刘苏曼 李茉白 语言 北大 博士 带 听歌 学 日语 小语种 日本语",
  "isOnLive": false,
  "playbackStatus": "done",
  "status": "finished",
  "introductionImages": [],
  "schedule": [{
    "_id": "5a4b4ab56584c340677be1f2",
    "endTime": "22:30",
    "startTime": "20:00",
    "name": "神奇的日语教学法——北大博士带你听歌学日语",
    "startDate": "2017-01-18T16:00:00.000Z"
  }],
  "type": "record",
  "likes": 11,
  "app": "uni",
  "numberOfClasses": 3,
  "teacherDescription": "刘苏曼，北京大学日语博士在读，著有《简单日语极速入门》。曾获第16届中日友好之声日语演讲比赛低年级组第1名，曾赴日本京都大学交换留学。多场口译、笔译、主持经验，曾负责东北亚学生论坛即席翻译。\n\n李茉白 。初一开始至今日语专业12年，保送北京外国语大学本硕；前新东方前人气日语教师 新教师PK赛第一名；前北京外国语大学日语二外教师；JLPT考试N1满分 日语专业八级优秀；CATTI全国翻译资格口译二级。\n\n",
  "teacherAvatar": "http://imgs.wanmen.org/6cd475b81fe753da4731cb2dba1c2259.png",
  "teacherName": "刘苏曼、李茉白",
  "mobileCoverUrl": "http://imgs.wanmen.org/7b50ce5178c08f7b75983a606dab1353.png",
  "coverUrl": "http://imgs.wanmen.org/99d08762c54636ae17564f7d9f39938a.png",
  "smallImageUrl": "http://imgs.wanmen.org/7b50ce5178c08f7b75983a606dab1353.png",
  "bigImageUrl": "http://imgs.wanmen.org/99d08762c54636ae17564f7d9f39938a.png",
  "id": "5879d4f90389ac22aad6d571",
  "isPaid": false,
  "remainingDays": -1,
  "isLiked": false,
  "isFaved": false,
  "history": null,
  "isPass": false,
  "lectures": [{
    "deletedAt": null,
    "deleted": false,
    "createdAt": "2017-09-30T07:23:57.006Z",
    "updatedAt": "2017-09-30T07:23:57.006Z",
    "courseId": "5879d4f90389ac22aad6d571",
    "name": "宣传片",
    "order": 0,
    "actions": {
      "download": false,
      "watch": false
    },
    "hide": false,
    "id": "59cf468d5c2b7e3cdd5e6514",
    "children": [{
      "deletedAt": null,
      "deleted": false,
      "createdAt": "2017-09-30T07:24:02.216Z",
      "updatedAt": "2017-09-30T07:24:18.540Z",
      "parentId": "59cf468d5c2b7e3cdd5e6514",
      "courseId": "5879d4f90389ac22aad6d571",
      "name": "宣传片",
      "order": 0,
      "video": {
        "hls": {
          "mobileLow": "http://media.wanmen.org/5c9e04d053e31ea590f11a8a41204fe3_mobile_low.m3u8",
          "pcLow": "http://media.wanmen.org/5c9e04d053e31ea590f11a8a41204fe3_pc_low.m3u8",
          "pcHigh": "http://media.wanmen.org/5c9e04d053e31ea590f11a8a41204fe3_pc_high.m3u8",
          "pcMid": "http://media.wanmen.org/5c9e04d053e31ea590f11a8a41204fe3_pc_mid.m3u8",
          "mobileMid": "http://media.wanmen.org/5c9e04d053e31ea590f11a8a41204fe3_mobile_mid.m3u8"
        },
        "id": "58ef16a9d5ff756f6344a9e0"
      },
      "actions": {
        "download": true,
        "watch": true
      },
      "hide": false,
      "id": "59cf469234e155210a4b5540",
      "hls": {
        "mobileLow": "http://media.wanmen.org/5c9e04d053e31ea590f11a8a41204fe3_mobile_low.m3u8",
        "pcLow": "http://media.wanmen.org/5c9e04d053e31ea590f11a8a41204fe3_pc_low.m3u8",
        "pcHigh": "http://media.wanmen.org/5c9e04d053e31ea590f11a8a41204fe3_pc_high.m3u8",
        "pcMid": "http://media.wanmen.org/5c9e04d053e31ea590f11a8a41204fe3_pc_mid.m3u8",
        "mobileMid": "http://media.wanmen.org/5c9e04d053e31ea590f11a8a41204fe3_mobile_mid.m3u8"
      }
    }]
  }, {
    "courseId": "5879d4f90389ac22aad6d571",
    "name": "听歌学日语-哆啦A梦主题曲",
    "createdAt": "2017-03-28T07:42:00.599Z",
    "order": 1,
    "description": null,
    "updatedAt": "2017-06-21T08:42:26.832Z",
    "actions": {
      "download": false,
      "watch": false
    },
    "hide": false,
    "id": "58da13c82f8052899cb79060",
    "children": [{
      "courseId": "5879d4f90389ac22aad6d571",
      "name": "哆啦A梦主题曲(1)",
      "parentId": "58da13c82f8052899cb79060",
      "createdAt": "2017-03-28T07:42:05.099Z",
      "order": 1,
      "updatedAt": "2017-12-22T02:28:25.416Z",
      "video": {
        "hls": {
          "mobileLow": "http://media.wanmen.org/641c4ba2a7f2e6748be237b7cb7eea86_mobile_low.m3u8",
          "pcLow": "http://media.wanmen.org/641c4ba2a7f2e6748be237b7cb7eea86_pc_low.m3u8",
          "pcHigh": "http://media.wanmen.org/641c4ba2a7f2e6748be237b7cb7eea86_pc_high.m3u8",
          "pcMid": "http://media.wanmen.org/641c4ba2a7f2e6748be237b7cb7eea86_pc_mid.m3u8",
          "mobileMid": "http://media.wanmen.org/641c4ba2a7f2e6748be237b7cb7eea86_mobile_mid.m3u8"
        },
        "id": "58ef16a9d5ff756f6344b1b3"
      },
      "from": "playback",
      "actions": {
        "download": true,
        "watch": true
      },
      "hls": {
        "mobileLow": "http://media.wanmen.org/641c4ba2a7f2e6748be237b7cb7eea86_mobile_low.m3u8",
        "pcLow": "http://media.wanmen.org/641c4ba2a7f2e6748be237b7cb7eea86_pc_low.m3u8",
        "pcHigh": "http://media.wanmen.org/641c4ba2a7f2e6748be237b7cb7eea86_pc_high.m3u8",
        "pcMid": "http://media.wanmen.org/641c4ba2a7f2e6748be237b7cb7eea86_pc_mid.m3u8",
        "mobileMid": "http://media.wanmen.org/641c4ba2a7f2e6748be237b7cb7eea86_mobile_mid.m3u8"
      },
      "hide": false,
      "id": "58da13cd2f8052899cb79061"
    }, {
      "courseId": "5879d4f90389ac22aad6d571",
      "name": "哆啦A梦主题曲(2)",
      "parentId": "58da13c82f8052899cb79060",
      "createdAt": "2017-03-28T07:42:05.116Z",
      "order": 2,
      "updatedAt": "2017-12-22T02:28:31.210Z",
      "video": {
        "hls": {
          "mobileLow": "http://media.wanmen.org/63d643fa26d5e53998d2d8deaa440b49_mobile_low.m3u8",
          "pcLow": "http://media.wanmen.org/63d643fa26d5e53998d2d8deaa440b49_pc_low.m3u8",
          "pcHigh": "http://media.wanmen.org/63d643fa26d5e53998d2d8deaa440b49_pc_high.m3u8",
          "pcMid": "http://media.wanmen.org/63d643fa26d5e53998d2d8deaa440b49_pc_mid.m3u8",
          "mobileMid": "http://media.wanmen.org/63d643fa26d5e53998d2d8deaa440b49_mobile_mid.m3u8"
        },
        "id": "58ef16a9d5ff756f6344b1b9"
      },
      "from": "playback",
      "actions": {
        "download": false,
        "watch": false
      },
      "hls": {},
      "hide": false,
      "id": "58da13cd2f8052899cb79062"
    }, {
      "courseId": "5879d4f90389ac22aad6d571",
      "name": "哆啦A梦主题曲(3)",
      "parentId": "58da13c82f8052899cb79060",
      "createdAt": "2017-03-28T07:42:05.128Z",
      "order": 3,
      "updatedAt": "2017-12-22T02:28:42.505Z",
      "video": {
        "hls": {
          "mobileLow": "http://media.wanmen.org/64ac6dae-99f9-4797-913a-27c22aefc716_mobile_low.m3u8",
          "pcLow": "http://media.wanmen.org/64ac6dae-99f9-4797-913a-27c22aefc716_pc_low.m3u8",
          "pcHigh": "http://media.wanmen.org/64ac6dae-99f9-4797-913a-27c22aefc716_pc_high.m3u8",
          "pcMid": "http://media.wanmen.org/64ac6dae-99f9-4797-913a-27c22aefc716_pc_mid.m3u8",
          "mobileMid": "http://media.wanmen.org/64ac6dae-99f9-4797-913a-27c22aefc716_mobile_mid.m3u8"
        },
        "id": "58f5725551f07446cca49ef7"
      },
      "from": "playback",
      "actions": {
        "download": false,
        "watch": false
      },
      "hls": {},
      "hide": false,
      "id": "58da13cd2f8052899cb79063"
    }]
  }, {
    "courseId": "5879d4f90389ac22aad6d571",
    "name": "听歌学日语-名侦探柯南主题曲",
    "createdAt": "2017-03-28T07:42:05.144Z",
    "order": 2,
    "description": null,
    "updatedAt": "2017-06-21T08:43:10.987Z",
    "actions": {
      "download": false,
      "watch": false
    },
    "hide": false,
    "id": "58da13cd2f8052899cb79064",
    "children": [{
      "courseId": "5879d4f90389ac22aad6d571",
      "name": "名侦探柯南主题曲(1)",
      "parentId": "58da13cd2f8052899cb79064",
      "createdAt": "2017-03-28T07:42:05.177Z",
      "order": 1,
      "updatedAt": "2017-12-22T02:28:51.860Z",
      "video": {
        "hls": {
          "mobileLow": "http://media.wanmen.org/75a78b24687f0bb66d45ebff5452dc59_mobile_low.m3u8",
          "pcLow": "http://media.wanmen.org/75a78b24687f0bb66d45ebff5452dc59_pc_low.m3u8",
          "pcHigh": "http://media.wanmen.org/75a78b24687f0bb66d45ebff5452dc59_pc_high.m3u8",
          "pcMid": "http://media.wanmen.org/75a78b24687f0bb66d45ebff5452dc59_pc_mid.m3u8",
          "mobileMid": "http://media.wanmen.org/75a78b24687f0bb66d45ebff5452dc59_mobile_mid.m3u8"
        },
        "id": "58ef16a9d5ff756f6344b1d4"
      },
      "from": "playback",
      "actions": {
        "download": false,
        "watch": false
      },
      "hls": {},
      "hide": false,
      "id": "58da13cd2f8052899cb79065"
    }, {
      "courseId": "5879d4f90389ac22aad6d571",
      "name": "名侦探柯南主题曲(2)",
      "parentId": "58da13cd2f8052899cb79064",
      "createdAt": "2017-03-28T07:42:05.190Z",
      "order": 2,
      "updatedAt": "2017-12-22T02:29:01.618Z",
      "video": {
        "hls": {
          "mobileLow": "http://media.wanmen.org/e35cffc506512a3299a8611aab50f688_mobile_low.m3u8",
          "pcLow": "http://media.wanmen.org/e35cffc506512a3299a8611aab50f688_pc_low.m3u8",
          "pcHigh": "http://media.wanmen.org/e35cffc506512a3299a8611aab50f688_pc_high.m3u8",
          "pcMid": "http://media.wanmen.org/e35cffc506512a3299a8611aab50f688_pc_mid.m3u8",
          "mobileMid": "http://media.wanmen.org/e35cffc506512a3299a8611aab50f688_mobile_mid.m3u8"
        },
        "id": "58ef16a9d5ff756f6344b1d5"
      },
      "from": "playback",
      "actions": {
        "download": false,
        "watch": false
      },
      "hls": {},
      "hide": false,
      "id": "58da13cd2f8052899cb79066"
    }, {
      "courseId": "5879d4f90389ac22aad6d571",
      "name": "名侦探柯南主题曲(3)",
      "parentId": "58da13cd2f8052899cb79064",
      "createdAt": "2017-03-28T07:42:05.203Z",
      "order": 3,
      "updatedAt": "2017-12-22T02:29:28.676Z",
      "video": {
        "hls": {
          "mobileLow": "http://media.wanmen.org/3a332c2c723be7d79fb51db50db5a099_mobile_low.m3u8",
          "pcLow": "http://media.wanmen.org/3a332c2c723be7d79fb51db50db5a099_pc_low.m3u8",
          "pcHigh": "http://media.wanmen.org/3a332c2c723be7d79fb51db50db5a099_pc_high.m3u8",
          "pcMid": "http://media.wanmen.org/3a332c2c723be7d79fb51db50db5a099_pc_mid.m3u8",
          "mobileMid": "http://media.wanmen.org/3a332c2c723be7d79fb51db50db5a099_mobile_mid.m3u8"
        },
        "id": "58ef16a9d5ff756f6344b1d6"
      },
      "from": "playback",
      "actions": {
        "download": false,
        "watch": false
      },
      "hls": {},
      "hide": false,
      "id": "58da13cd2f8052899cb79067"
    }, {
      "courseId": "5879d4f90389ac22aad6d571",
      "name": "名侦探柯南主题曲(4)",
      "parentId": "58da13cd2f8052899cb79064",
      "createdAt": "2017-03-28T07:42:05.219Z",
      "order": 4,
      "updatedAt": "2017-12-22T02:29:39.251Z",
      "video": {
        "hls": {
          "mobileLow": "http://media.wanmen.org/d5ebf661f9e8ac5d3a1d5067caedb671_mobile_low.m3u8",
          "pcLow": "http://media.wanmen.org/d5ebf661f9e8ac5d3a1d5067caedb671_pc_low.m3u8",
          "pcHigh": "http://media.wanmen.org/d5ebf661f9e8ac5d3a1d5067caedb671_pc_high.m3u8",
          "pcMid": "http://media.wanmen.org/d5ebf661f9e8ac5d3a1d5067caedb671_pc_mid.m3u8",
          "mobileMid": "http://media.wanmen.org/d5ebf661f9e8ac5d3a1d5067caedb671_mobile_mid.m3u8"
        },
        "id": "58ef16a9d5ff756f6344b1d7"
      },
      "from": "playback",
      "actions": {
        "download": false,
        "watch": false
      },
      "hls": {},
      "hide": false,
      "id": "58da13cd2f8052899cb79068"
    }]
  }, {
    "courseId": "5879d4f90389ac22aad6d571",
    "name": "听歌学日语-犬夜叉主题曲",
    "createdAt": "2017-03-28T07:42:05.233Z",
    "order": 3,
    "description": null,
    "updatedAt": "2017-06-21T08:43:15.940Z",
    "actions": {
      "download": false,
      "watch": false
    },
    "hide": false,
    "id": "58da13cd2f8052899cb79069",
    "children": [{
      "courseId": "5879d4f90389ac22aad6d571",
      "name": "犬夜叉主题曲(1)",
      "parentId": "58da13cd2f8052899cb79069",
      "createdAt": "2017-03-28T07:42:05.262Z",
      "order": 1,
      "updatedAt": "2017-12-22T02:29:47.180Z",
      "video": {
        "hls": {
          "mobileLow": "http://media.wanmen.org/8f1a8d1959ca67c1209d29bbfe57469c_mobile_low.m3u8",
          "pcLow": "http://media.wanmen.org/8f1a8d1959ca67c1209d29bbfe57469c_pc_low.m3u8",
          "pcHigh": "http://media.wanmen.org/8f1a8d1959ca67c1209d29bbfe57469c_pc_high.m3u8",
          "pcMid": "http://media.wanmen.org/8f1a8d1959ca67c1209d29bbfe57469c_pc_mid.m3u8",
          "mobileMid": "http://media.wanmen.org/8f1a8d1959ca67c1209d29bbfe57469c_mobile_mid.m3u8"
        },
        "id": "58ef16a9d5ff756f6344b1d8"
      },
      "from": "playback",
      "actions": {
        "download": false,
        "watch": false
      },
      "hls": {},
      "hide": false,
      "id": "58da13cd2f8052899cb7906a"
    }, {
      "courseId": "5879d4f90389ac22aad6d571",
      "name": "犬夜叉主题曲(2)",
      "parentId": "58da13cd2f8052899cb79069",
      "createdAt": "2017-03-28T07:42:05.273Z",
      "order": 2,
      "updatedAt": "2017-12-22T02:29:52.646Z",
      "video": {
        "hls": {
          "mobileLow": "http://media.wanmen.org/60513aaae2b975ee4831ef6e595f6435_mobile_low.m3u8",
          "pcLow": "http://media.wanmen.org/60513aaae2b975ee4831ef6e595f6435_pc_low.m3u8",
          "pcHigh": "http://media.wanmen.org/60513aaae2b975ee4831ef6e595f6435_pc_high.m3u8",
          "pcMid": "http://media.wanmen.org/60513aaae2b975ee4831ef6e595f6435_pc_mid.m3u8",
          "mobileMid": "http://media.wanmen.org/60513aaae2b975ee4831ef6e595f6435_mobile_mid.m3u8"
        },
        "id": "58ef16a9d5ff756f6344b1d9"
      },
      "from": "playback",
      "actions": {
        "download": false,
        "watch": false
      },
      "hls": {},
      "hide": false,
      "id": "58da13cd2f8052899cb7906b"
    }]
  }],
  "hasTopic": false
}